toml_combine/__init__.py
toml_combine/__main__.py
toml_combine/cli.py
toml_combine/combiner.py
toml_combine/exceptions.py
toml_combine/lib.py
toml_combine/toml.py
toml_combine-1.0.3.dist-info/METADATA
toml_combine-1.0.3.dist-info/WHEEL
toml_combine-1.0.3.dist-info/entry_points.txt
toml_combine-1.0.3.dist-info/licenses/LICENSE
toml_combine-1.0.3.dist-info/RECORD
